{"id":"16g41q2","title":"Using any website, you can extract data, monitor it, and create APIs with Browse.ai","author":"AIInformer","created_utc":1694459126,"score":1,"selftext":"","url":"https://v.redd.it/xtye75gpconb1","comments":[{"id":"k05eb5e","author":"AIInformer","body":"Introducing Browse.ai, the all-in-one solution that empowers you to extract, monitor, and create APIs for seamless data integration. With Browse.ai, you can effortlessly extract valuable data from diverse sources, including web pages, documents, and social media platforms. Our advanced algorithms ensure accurate and efficient data collection, providing you with the insights you need to fuel your business growth. Stay ahead of the competition with real-time data monitoring, enabling you to track trends, monitor competitors, and make informed decisions. Additionally, Browse.ai allows you to create APIs, enabling easy integration of data into your existing systems and workflows. Streamline your data processes and unlock the true potential of your business with Browse.ai's comprehensive data extraction, monitoring, and API creation capabilities.  \nhttps://browse.ai/?via=extractmonitorapi","score":1,"created_utc":1694459140,"is_op":true,"replies":[]}]}