{"id":"1n8239o","title":"Trading-Tipp für Anfänger: Bearish Break of Structure (BoS) erklärt!","author":"AkiraBTC4U","created_utc":1756964983,"score":1,"selftext":"Hey Neulinge! 📈 Lernt mit diesem Chart, wie ein Bearish BoS funktioniert (EUR/USD, 1-Stunden-Chart):\nAufwärtstrend: Höhere Hochs (HH1 bei 1.1100, HH2 bei 1.1200) und höhere Tiefs (HL1 bei 1.0950, Höheres Tief bei 1.1000).\nBoS: Der Preis fällt unter das letzte Höhere Tief (1.1000) – ein Bearish BoS, Signal für eine mögliche Abwärtskorrektur!\nTrading-Idee: Warte auf einen Retest von 1.1000 als Widerstand, dann Short mit Stop-Loss über HH2 (1.1200) und Ziel bei 1.0950 oder Fibonacci-Levels (z. B. 50 % bei 1.1050).\nTipps:\nÜbe auf einem Demokonto (z. B. TradingView).\nNutze Fibonacci für Ziele oder Unterstützung.\nRiskiere nur 1-2 % pro Trade!\nFragen? Kommentiert! #TradingFürAnfänger #BoS #TechnischeAnalyse","url":"https://i.redd.it/y4uq9yyx63nf1.png","comments":[]}