{"id":"1ojgaqz","title":"I used an AI agent to create my trading strategy and the results are insane","author":"TheReaIIronMan","created_utc":1761771207,"score":0,"selftext":"I used an autonomous AI to create a trading strategy and the end result is unbelievable. With a single prompt, the AI autonomously performed financial research and created several profitable trading strategies. Strategies, optimize them, and help me understand how the strategies will perform in the real world.\n\nThe AI is called Aurora and I think this is the future [vibe trading](https://medium.com/@austin-starks/vibe-trading-how-the-best-traders-actually-use-ai-and-how-not-to-blow-up-your-account-90543b5c9d68). Has anybody else used AI to create trading strategies? What was your experience?","url":"https://nexustrade.io/share/agent/690277bde0325d2d4c34f0cb","comments":[{"id":"nm2ujbf","author":"Sofullofsplendor_","body":"ad","score":2,"created_utc":1761771942,"is_op":false,"replies":[{"id":"nm2xy5q","author":"TheReaIIronMan","body":"An ad for a free AI trading tool on the ai_trading subreddit? Do you know what ad means?","score":-1,"created_utc":1761772926,"is_op":true,"replies":[]}]},{"id":"nm39ats","author":"eightaceman","body":"Why is everything insane these days","score":1,"created_utc":1761776349,"is_op":false,"replies":[]}]}