{"id":"1otgfsj","title":"QQQ's 1-Month Outlook: Key Technical Levels Signaling Now","author":"henryzhangpku","created_utc":1762787805,"score":1,"selftext":"Just analyzed QQQ's 1-month chart pattern - and the setup looks significant.\n\nHere's what caught my attention: • QQQ approaching critical support level that historically precedes 5-8% moves • RSI divergence suggesting potential momentum shift • Volume profile showing institutional accumulation at current levels • Key resistance breakout would confirm bullish continuation pattern\n\nThe 1-month timeframe is particularly interesting given upcoming Fed meeting and earnings season overlap. This could be the swing trade setup many are watching for.\n\nFull technical breakdown includes:\n\n* Exact entry/exit levels with risk management\n* Probability-weighted scenarios based on historical data\n* How this aligns with broader market sector rotation\n\nI've mapped out the three most likely price paths with corresponding trade setups. The analysis goes deeper into why this particular technical confluence matters more than usual right now.\n\nDrop a comment if you want me to share which sector ETFs would amplify this trade setup. Full technical deep dive ready for serious traders.\n\nWhat's your take on QQQ's near-term direction?\n\n🔗 [https://discord.gg/quantsignals](https://discord.gg/quantsignals)...\n\n🔥 Unlock full content:  [https://discord.gg/quantsignals](https://discord.gg/quantsignals)\n\nhttps://preview.redd.it/xeabp6r65g0g1.png?width=2085&format=png&auto=webp&s=2543491395853346ae9f2bbd7baac81eccb0da2d","url":"https://www.reddit.com/r/ai_trading/comments/1otgfsj/qqqs_1month_outlook_key_technical_levels/","comments":[]}