{"id":"1rurzhu","title":"Newsflash #4 is out — added to NST on Monday, it dropped 18% on Friday","author":"StackMotive","created_utc":1773613921,"score":2,"selftext":"","url":"/r/StackMotive/comments/1ruryt8/newsflash_4_is_out_added_to_nst_on_monday_it/","comments":[{"id":"oapoawp","author":"bjxxjj","body":"An 18% drop right after being added to NST isn’t that unusual, especially if there was a run‑up into the inclusion. A lot of names get bid up on anticipation, then see a “sell the news” reaction once the actual addition happens.\n\nI’d be looking at a few things before drawing conclusions:\n\n- Was volume elevated on Friday? If so, that could indicate institutional repositioning rather than pure panic selling.  \n- Any broader sector weakness or macro headlines that might have amplified the move?  \n- Valuation going into the news — was it already stretched?\n\nIndex additions can create short-term volatility, but they don’t change fundamentals. If the underlying thesis hasn’t changed, this could just be noise. If the drop coincided with new guidance or material info, that’s different.\n\nCurious if anyone here was tracking options flow or short interest around the inclusion. That might give more context to the move.","score":1,"created_utc":1773647409,"is_op":false,"replies":[]},{"id":"oapuzvd","author":"StackMotive","body":"Good points and you’re right, the sell-the-news pattern on index additions is real. But in this case there was more going on.\nThe platform I’m running had been firing sustained bearish CONVERGENCE alerts on NST every single day from 6 March, a full seven days before the crash. Price had dropped below SMA50, MACD histogram was deepening negative daily (-0.41 by 9 March, -0.51 by 10 March), and the signals were HIGH severity throughout. By the evening of 12 March it had fired 10+ bearish CONVERGENCE alerts.\nOn your volume question, yes Friday volume came in at 2.1x normal. RSI hit 29.7 at close. The platform flagged both.\nOn short interest, I don’t have clean short volume ratio data for NST in the pre-crash window so I won’t claim I do. What I did have was seven days of technical deterioration while the company was publicly reporting record EBITDA. The technicals and the fundamentals were telling completely different stories.\nThe honest takeaway: the DCA rule fired on price action alone on Monday 9 March. The broader signal stack had been bearish for three days at that point. That’s the tension that will be at the core of Newsflash #5, Newsflash #4 documents the rule-based add, #5 will cover what the full signal picture actually looked like and what I should have done with it !!","score":1,"created_utc":1773651486,"is_op":true,"replies":[]}]}