{"id":"1sovae5","title":"My Monthly Online Income Is $486","author":"PersonalityRound9290","created_utc":1776512244,"score":1,"selftext":"Recently, a friend of mine told me that he came across a post by user [waltwhiteee](https://www.reddit.com/search/?q=waltwhiteee&type=people&cId=9df87f10NBVC) and his method of earning money, thanks to which he has already earned about $150. Yes, this is far from the limit of earnings, and I understand that you can't earn much there, but it's still enough to cover some small expenses. By the way, the method still works. Maybe someone will find it interesting. Here is his profile: [waltwhiteee](https://www.reddit.com/search/?q=waltwhiteee&type=people&cId=9df87f10NBVC)","url":"https://www.reddit.com/r/ai_trading/comments/1sovae5/my_monthly_online_income_is_486/","comments":[]}