{"id":"1t0ypbc","title":"Us30 analysis by Chozen indicator","author":"Siyabonga_TheGreat","created_utc":1777653710,"score":1,"selftext":"I will be honest Chozen 3.0 it not magic system It’s a precision tool. I’ve traded US30 for the last 5 days without a loss, but that’s because I followed the system Wait for the level breakout, then execute.\n\nIf you don’t have the patience to wait for the setup, don’t try this. But if you want a powerful, easy to use system.\n\n\nhttps://whop.com/chozen-trading-systems/","url":"https://v.redd.it/o2fm10b51kyg1","comments":[]}