{"id":"1t6fxyd","title":"Each transaction exceeds 100%.","author":"Ok-Basil2753","created_utc":1778172020,"score":1,"selftext":"Every week, I share my watchlist, market observations, and risk analysis. All content is completely free of charge; I do not provide trading signals, promote paid tools, or offer any guarantees of profit.\n\nI have compiled these materials into a dedicated folder, which I have pinned to the top of my stock discussion group. If you are interested in this analytical approach, please feel free to leave a comment or send me a private message I would be happy to share my insights with you.","url":"https://i.redd.it/1f4rievbuqzg1.jpeg","comments":[]}