{"id":"1tutm86","title":"Trade ideas for this week","author":"Magic-Mike-2023","created_utc":1780412584,"score":1,"selftext":"Hey everyone!   \nI was on vacation for two weeks and didn't do any posts, but now I'm back 😄  \nAs always I've prepared a list of ideas for this week from my [Cyclical Barbell](https://builder.limex.com/dashboard/104089) strategy.\n\nI wanted to know if someone wants to join a free webinar. The topic will be - How to pick and stocks in current market situation using Alpha Builder. I'm planning to do it in couple of weeks so if you interested, upvote this post or drop a comment. I will make a separate post with registration link.\n\n**Stock Analysis: Growth Reasoning & Downside Risks**\n\n|Company|Why Picked|Entry Target|Exit (Profit)|Stop Loss|Growth Reasoning|Specific Event for Price Drop|\n|:-|:-|:-|:-|:-|:-|:-|\n|**Snap-on** [NYSE:SNA](https://www.google.com/finance/beta/quote/SNA:NYSE)|Strong fundamentals & 29% historical momentum.|$365.00|$405.00|$350.00|Consistent net profit margins (\\~20%) and high EPS ($19.52 in 2025) driven by professional tool demand.|**Auto Repair Slowdown:** A sharp contraction in consumer spending on vehicle maintenance, reducing tool replacement cycles.|\n|**Myers Industries** [NYSE:MYE](https://www.google.com/finance/beta/quote/MYE:NYSE)|\"Focused Transformation\" & 17% momentum.|$22.50|$26.00|$20.50|Profitability surge from operational restructuring, despite modest revenue growth.|**Infrastructure Delay:** A federal freeze on new construction projects impacting their material handling and infrastructure segments.|\n|**Baker Hughes** [NASDAQ:BKR](https://www.google.com/finance/beta/quote/BKR:NASDAQ)|Energy sector yield & 15% growth.|$64.00|$78.00|$59.00|Exceptional 1-year return (\\~80%) and high free cash flow generation from global energy tech demand.|**CapEx Freeze:** Major oil producers slashing exploration budgets due to a sudden, sustained drop in crude prices.|\n|**Avnet** [NASDAQ:AVT](https://www.google.com/finance/beta/quote/AVT:NASDAQ)|Sector benchmark & 5.5% stability.|$85.00|$95.00|$81.00|Positioned as a key electronics distributor benefiting from stable financial growth trends in hardware.|**Chip Oversupply:** A sudden glut in semiconductor inventory leading to reduced distribution margins.|\n|**AudioCodes** [NASDAQ:AUDC](https://www.google.com/finance/beta/quote/AUDC:NASDAQ)|High R&D focus & hardware sector position.|$9.50|$12.00|$8.80|Heavy investment in R&D (\\~$52M) to maintain edge in communications hardware and cloud networking.|**Enterprise Tech Cutback:** Global shift away from legacy hardware toward pure-software VOIP solutions.|\n|**Karooooo** [NASDAQ:KARO](https://www.google.com/finance/beta/quote/KARO:NASDAQ)|20% Revenue growth & IoT scalability.|$46.50|$63.00|$42.00|Strong subscription growth (19%) and massive 90% increase in adjusted free cash flow for FY 2026.|**FX Headwinds:** Significant depreciation of the South African Rand or other emerging market currencies against the USD.|\n|**Vale** [NYSE:VALE](https://www.google.com/finance/beta/quote/VALE:NYSE)|Base metals transition & high dividend yield.|$15.50|$18.50|$14.50|Shift toward copper and nickel for the energy transition, supported by record copper prices above $6/lb.|**Steel Demand Crash:** A deeper-than-expected economic slowdown in China causing iron ore prices to plunge below $85/ton.|\n\n# Summary of Risks\n\n* **Operational Transformation Risks:** For **Myers Industries (MYE)**, the current growth story relies heavily on internal cost-cutting and portfolio optimization. If these initiatives plateau before top-line growth recovers, the valuation could revert quickly.\n* **Currency & Regional Exposure:** **Karooooo (KARO)** remains highly exposed to the South African market. Despite stellar IoT subscriber growth, geopolitical instability or currency volatility in that region can wipe out gains for USD-based investors.\n* **Commodity Volatility:** **Vale (VALE)** and **Baker Hughes (BKR)** are inherently cyclical. While they are diversifying into \"green\" metals and tech, their short-term price action is still largely dictated by the spot prices of iron ore and crude oil.","url":"https://www.reddit.com/r/ai_trading/comments/1tutm86/trade_ideas_for_this_week/","comments":[{"id":"ophviha","author":"lesbian_boii","body":"Good post op","score":2,"created_utc":1780486833,"is_op":false,"replies":[]}]}