{"id":"jvwhfh","title":"(Bullish Signal) NUS, Triangle Ascending","author":"tickeron_community","created_utc":1605631981,"score":1,"selftext":"STATUS = Confirmed\n\nCURRENT CONFIDENCE = 70%\n\nTARGET (EXIT) PRICE = 52.67 USD\n\nBREAKOUT (ENTRY) PRICE = 52.10 USD\n\nDISTANCE TO TARGET PRICE = 0.65%\n\nEMERGED ON = Nov 17, 10:00 AM (EST)\n\nCONFIRMED ON = Nov 17, 11:02 AM (EST)\n\nWITH CONFIDENCE LEVEL = 74%\n\nhttps://preview.redd.it/ddg69e9lytz51.png?width=1447&format=png&auto=webp&s=d9fcafa3948c4eaf29003bc668cc0a37e97c5d5a\n\nThe Ascending Triangle pattern forms when the price of a security tests a resistance level and creates a horizontal top line (1, 3, 5), with an upward­-sloping bottom line (2, 4) formed by a rising support level. The breakout can either be up or down, and it will determine whether the target price is higher or lower.\n\nThis pattern is commonly associated with directionless markets, since the contraction (narrowing) of the market range signals that neither bulls nor bears are in control. When the price of a security consolidates around a certain level, it may indicate growing investor confidence for a significant uptrend.\n\n**Trade idea**\n\nOnce price breaks outside of the triangle, day traders and swing traders should trade with an UP trend. Consider buying a security at the upward breakout level. To identify an exit, compute the target price by adding the pattern height to the breakout point. For upward breakouts, the level is the top horizontal line (1, 3, 5). The pattern height can be calculated by taking the difference between the resistance level set by the horizontal line, and the lowest low.\n\nTo limit potential loss when price suddenly goes in the wrong direction, consider placing a stop order to sell at or below the breakout price.","url":"https://www.reddit.com/r/ai_trading/comments/jvwhfh/bullish_signal_nus_triangle_ascending/","comments":[]}